Rit/Rit.py
Rit/__init__.py
Rit/gui.py
Rit/jalali.py
Rit-1.0.1.dist-info/LICENSE
Rit-1.0.1.dist-info/METADATA
Rit-1.0.1.dist-info/WHEEL
Rit-1.0.1.dist-info/entry_points.txt
Rit-1.0.1.dist-info/top_level.txt
Rit-1.0.1.dist-info/RECORD
