Metadata-Version: 2.1
Name: Rit
Version: 1.0.1
Summary: Rit Rename your photos :)
Home-page: https://github.com/mo1ein/RenameIt
Author: Moein Halvaei
Author-email: moeinn.com@gmail.com
License: GPLv3+
Platform: UNKNOWN
Classifier: Intended Audience :: Developers
Classifier: Natural Language :: English
Classifier: License :: OSI Approved :: GNU General Public License v3 or later (GPLv3+)
Classifier: Operating System :: OS Independent
Classifier: Programming Language :: Python :: 3
Classifier: Programming Language :: Python :: 3.4
Classifier: Programming Language :: Python :: 3.5
Classifier: Programming Language :: Python :: 3.6
Classifier: Programming Language :: Python :: 3.7
Classifier: Programming Language :: Python :: 3.8
Classifier: Programming Language :: Python :: Implementation :: CPython
Classifier: Programming Language :: Python :: Implementation :: PyPy
Classifier: Topic :: Software Development :: Libraries
Classifier: Topic :: Software Development :: Libraries :: Python Modules
Classifier: Topic :: Software Development :: Localization
Classifier: Topic :: Utilities
Requires-Dist: persiantools
Requires-Dist: pillow
Requires-Dist: pyqt5
Requires-Dist: pytz
